Metadata-Version: 2.1
Name: nobi-pytezos
Version: 0.1.2
Summary: Python toolkit for Tezos
Home-page: https://github.com/nobbennob/nobi-pytezos
License: MIT
Keywords: tezos,blockchain,sdk,michelson,repl,cryptocurrencies,smart-contracts,jupyter,ipython,docker,crypto
Author: Michael Zaikin
Author-email: mz@baking-bad.org
Maintainer: Lev Gorodetskii
Maintainer-email: pytezos@drsr.io
Requires-Python: >=3.8.1,<3.13
Classifier: Development Status :: 5 - Production/Stable
Classifier: Environment :: Console
Classifier: Framework :: IPython
Classifier: Intended Audience :: Developers
Classifier: License :: OSI Approved :: MIT License
Classifier: Operating System :: OS Independent
Classifier: Programming Language :: Python :: 3
Classifier: Programming Language :: Python :: 3.9
Classifier: Programming Language :: Python :: 3.10
Classifier: Programming Language :: Python :: 3.11
Classifier: Programming Language :: Python :: 3.12
Classifier: Programming Language :: Python :: 3.8
Classifier: Programming Language :: Python :: Implementation :: CPython
Classifier: Topic :: Software Development :: Libraries :: Application Frameworks
Classifier: Typing :: Typed
Requires-Dist: attrs (>=21.4.0,<=24.2.0)
Requires-Dist: base58 (>=2.0.1,<=2.1.1)
Requires-Dist: cattrs (>=22.1.0)
Requires-Dist: click (>=8.1.3)
Requires-Dist: coincurve (>=15.0.1,<18.0.0)
Requires-Dist: cryptography (>=3.4.6,<=42.0.0)
Requires-Dist: deprecation (>=2.1.0)
Requires-Dist: docker (>=6.0.0)
Requires-Dist: eth-utils (>=1.9.5,<2.0.0)
Requires-Dist: fastecdsa (>=2.2.3)
Requires-Dist: hexbytes (>=0.1.0,<1)
Requires-Dist: jsonschema (>=3.2.0,<4.0.0)
Requires-Dist: mnemonic (>=0.20,<0.21)
Requires-Dist: netstruct (>=1.1.2)
Requires-Dist: notebook (>=6.5,<7)
Requires-Dist: ply (>=3.11)
Requires-Dist: py-ecc (<7.0.0)
Requires-Dist: pysodium (>=0.7.10)
Requires-Dist: python-dateutil (>=2.8.2)
Requires-Dist: requests (>=2.28.2)
Requires-Dist: simple-bson (>=0.0.3)
Requires-Dist: simplejson (>=3.17.6)
Requires-Dist: strict-rfc3339 (>=0.7)
Requires-Dist: tabulate (>=0.9.0)
Requires-Dist: testcontainers (>=3.7.0,<4.8.0)
Requires-Dist: tornado (>=6.1,<=6.4.1)
Requires-Dist: tqdm (>=4.62.3)
Project-URL: Repository, https://github.com/nobbennob/nobi-pytezos
